brozzler/__init__.py
brozzler/behaviors.yaml
brozzler/browser.py
brozzler/chrome.py
brozzler/cli.py
brozzler/easy.py
brozzler/frontier.py
brozzler/job_schema.yaml
brozzler/metrics.py
brozzler/model.py
brozzler/pywb.py
brozzler/robots.py
brozzler/worker.py
brozzler/ydl.py
brozzler/dashboard/__init__.py
brozzler/dashboard/static/brozzler-icon.svg
brozzler/dashboard/static/brozzler.svg
brozzler/dashboard/static/js/app.js
brozzler/dashboard/static/partials/home.html
brozzler/dashboard/static/partials/job.html
brozzler/dashboard/static/partials/site.html
brozzler/dashboard/static/partials/workers.html
brozzler/dashboard/templates/index.html
brozzler/js-templates/extract-outlinks.js
brozzler/js-templates/fec_gov.js
brozzler/js-templates/huffpostslides.js
brozzler/js-templates/marquette_edu.js
brozzler/js-templates/psu24.js
brozzler/js-templates/stealth.js
brozzler/js-templates/try-login.js.j2
brozzler/js-templates/umbraBehavior.js.j2
brozzler_ia-1.6.1.dist-info/METADATA
brozzler_ia-1.6.1.dist-info/WHEEL
brozzler_ia-1.6.1.dist-info/entry_points.txt
brozzler_ia-1.6.1.dist-info/top_level.txt
brozzler_ia-1.6.1.dist-info/RECORD
