Metadata-Version: 2.1
Name: brozzler_ia
Version: 1.6.1
Summary: Distributed web crawling with browsers
Home-page: https://github.com/internetarchive/brozzler
Author: Noah Levitt
Author-email: Noah Levitt <nlevitt@archive.org>
Maintainer-email: Vangelis Banos <vangelis@archive.org>, Adam Miller <adam@archive.org>, Barbara Miller <barbara@archive.org>, Alex Dempsey <avdempsey@archive.org>
License: Apache License 2.0
Project-URL: Homepage, https://github.com/internetarchive/brozzler
Project-URL: Issues, https://github.com/internetarchive/brozzler/issues
Classifier: Programming Language :: Python :: 3
Classifier: License :: OSI Approved :: Apache Software License
Classifier: Operating System :: OS Independent
Requires-Python: >=3.8
Requires-Dist: PyYAML >=5.1
Requires-Dist: reppy ==0.3.4
Requires-Dist: requests >=2.21
Requires-Dist: websocket-client ==1.8.0
Requires-Dist: pillow >=5.2.0
Requires-Dist: urlcanon >=0.1.dev23
Requires-Dist: cerberus >=1.0.1
Requires-Dist: jinja2 >=2.10
Requires-Dist: cryptography >=2.3
Requires-Dist: python-magic >=0.4.15
Requires-Dist: prometheus-client >=0.20.0
Provides-Extra: dashboard
Requires-Dist: flask >=1.0 ; extra == 'dashboard'
Requires-Dist: gunicorn >=19.8.1 ; extra == 'dashboard'
Provides-Extra: easy
Requires-Dist: warcprox >=2.4.31 ; extra == 'easy'
Requires-Dist: pywb <2,>=0.33.2 ; extra == 'easy'
Requires-Dist: flask >=1.0 ; extra == 'easy'
Requires-Dist: gunicorn >=19.8.1 ; extra == 'easy'
Requires-Dist: rethinkdb ==2.4.9 ; extra == 'easy'
Requires-Dist: doublethink ==0.4.9 ; extra == 'easy'
Provides-Extra: yt-dlp
Requires-Dist: yt-dlp >=2024.7.25 ; extra == 'yt-dlp'
